{
  "roles": [
    {
      "name": "director",
      "username": "director@abmail.co.za",
      "password": "Test1234",
      "description": "Sarah Director — Director role with highest permissions"
    },
    {
      "name": "pm",
      "username": "pm@abmail.co.za",
      "password": "Test1234",
      "description": "James ProjectManager — Project Manager role"
    },
    {
      "name": "analyst",
      "username": "analyst@abmail.co.za",
      "password": "Test1234",
      "description": "Emily Analyst — Analyst role with basic permissions"
    }
  ],
  "login": {
    "url_path": "/login",
    "username_field": "email",
    "password_field": "password",
    "submit_button": "Sign In"
  }
}
